ansys/codefest/mapdl/__init__.py
ansys/codefest/mapdl/constants.py
ansys/codefest/mapdl/main.py
ansys/codefest/mapdl/tools.py
ansys/codefest/mapdl/validation.py
ansys/codefest/mapdl/chambers/__init__.py
ansys/codefest/mapdl/chambers/geometry_0.json
ansys/codefest/mapdl/chambers/geometry_10.json
ansys/codefest/mapdl/chambers/geometry_11.json
ansys/codefest/mapdl/chambers/geometry_1a.json
ansys/codefest/mapdl/chambers/geometry_1b.json
ansys/codefest/mapdl/chambers/geometry_2.json
ansys/codefest/mapdl/chambers/geometry_3.json
ansys/codefest/mapdl/chambers/geometry_4.json
ansys/codefest/mapdl/chambers/geometry_5.json
ansys/codefest/mapdl/chambers/geometry_6.json
ansys/codefest/mapdl/chambers/geometry_7.json
ansys/codefest/mapdl/chambers/geometry_8.json
ansys/codefest/mapdl/chambers/geometry_9.json
ansys/codefest/mapdl/chambers/suggestion_11.json
ansys/codefest/mapdl/chambers/suggestion_1a.json
ansys/codefest/mapdl/chambers/suggestion_1b.json
ansys/codefest/mapdl/chambers/suggestion_2.json
ansys/codefest/mapdl/chambers/suggestion_3.json
ansys/codefest/mapdl/mechanics/__init__.py
ansys/codefest/mapdl/mechanics/core.py
ansys/codefest/mapdl/setup/__init__.py
ansys/codefest/mapdl/setup/core.py
ansys/codefest/mapdl/story/__init__.py
ansys/codefest/mapdl/story/concise.txt
ansys/codefest/mapdl/story/example.py
ansys/codefest/mapdl/story/minimal.txt
ansys/codefest/mapdl/story/simplest_mapdl_example.py
ansys/codefest/mapdl/story/verbose.txt
ansys_codefest-0.2.0.dist-info/LICENSE
ansys_codefest-0.2.0.dist-info/WHEEL
ansys_codefest-0.2.0.dist-info/METADATA
ansys_codefest-0.2.0.dist-info/RECORD
