Metadata-Version: 2.3
Name: ansys-codefest
Version: 0.2.0
Summary: Ansys Codefest Companion Library
Author-email: "ANSYS, Inc." <pyansys.core@ansys.com>
Maintainer-email: "ANSYS, Inc." <pyansys.core@ansys.com>
Requires-Python: >=3.11,<4
Classifier: Development Status :: 4 - Beta
Classifier: Intended Audience :: Science/Research
Classifier: Topic :: Scientific/Engineering :: Information Analysis
Classifier: License :: OSI Approved :: MIT License
Classifier: Operating System :: OS Independent
Classifier: Programming Language :: Python :: 3.11
Classifier: Programming Language :: Python :: 3.12
Classifier: Programming Language :: Python :: 3.13
Requires-Dist: Markdown>=3.6
Requires-Dist: matplotlib>=3.9.0
Requires-Dist: ipython>=8.10.0
Requires-Dist: ansys-mapdl-core>0.68.0
Requires-Dist: jupyter>=1.0.0
Requires-Dist: pytest >=2.7.3 ; extra == "test"
Requires-Dist: pytest-cov ; extra == "test"
Requires-Dist: pre-commit ; extra == "test"
Requires-Dist: pytest-rerunfailures ; extra == "test"
Requires-Dist: pytest-cov ; extra == "test"
Provides-Extra: test
